django_url_helper/__init__.py
django_url_helper/test.py
django_url_helper/utils.py
django_url_helper/templatetags/__init__.py
django_url_helper/templatetags/url_helper.py
django_url_helper-0.0.1.dist-info/LICENSE
django_url_helper-0.0.1.dist-info/METADATA
django_url_helper-0.0.1.dist-info/WHEEL
django_url_helper-0.0.1.dist-info/top_level.txt
django_url_helper-0.0.1.dist-info/RECORD
